<?xml version="1.0" encoding="utf-8"?>
<base xmlns:xsi="http://www.w3.org/2001/XMLSchema-instance" xmlns:xsd="http://www.w3.org/2001/XMLSchema" type="string">
  <tags>
    <tag language="Türkçe"/>
  </tags>
  <strings>
    <string id="0Ikzzm71" text="Начальник Морской Бой "/>
    <string id="0qDNS83n" text="Бандит Номад "/>
    <string id="9laVlEH9" text="Горцы"/>
    <string id="Awc23bFS" text="Мародер"/>
    <string id="Bg63YFnh" text="Босс Степной Бандит "/>
    <string id="C1Fkzdvu" text="Босс Морской Бой "/>
    <string id="C8DE6L73" text="Дезертир"/>
    <string id="cbnvgVhH" text="Налетчик"/>
    <string id="cdbSCr6G" text="Харами"/>
    <string id="dc2qxanZ" text="Начальник Лесного Бандита "/>
    <string id="dq2cP8h0" text="Морской Бой"/>
    <string id="HadsURl8" text="Bushwacker"/>
    <string id="Nr8NkHXU" text="Морской Бой Воин"/>
    <string id="P6Md9DpR" text="Разбойник"/>
    <string id="Q2V4uQrr" text="Босс Бандита Пустыни "/>
    <string id="sFgODQ1q" text="Лесной Бандит"/>
    <string id="uOAnHN47" text="Бедуин Ровер"/>
    <string id="urUwa4bf" text="Мародер"/>
    <string id="ZA4bgJ5V" text="Степной Бандит"/>
    <string id="ziOBJSzR" text="Начальник Горного Бандита "/>
    <string id="ZKdiaaFo" text="Разбойник"/>
    <string id="ZxmBdWTu" text="Флибустьер"/>
  </strings>
</base>
